pond_agent/__init__.py
pond_agent/llm.py
pond_agent/logging_config.py
pond_agent/tools.py
pond_agent/competition/__init__.py
pond_agent/competition/agent.py
pond_agent/competition/base.py
pond_agent/competition/bug_fixer.py
pond_agent/competition/data_processor.py
pond_agent/competition/feature_engineer.py
pond_agent/competition/model_builder.py
pond_agent/competition/scraper.py
pond_agent/competition/submission_generator.py
pond_agent/competition/utils.py
pond_agent/competition/prompts/bug_fixer_system.txt
pond_agent/competition/prompts/bug_fixer_user.txt
pond_agent/competition/prompts/competition_agent_system.txt
pond_agent/competition/prompts/competition_agent_user.txt
pond_agent/competition/prompts/data_processor_system.txt
pond_agent/competition/prompts/data_processor_user.txt
pond_agent/competition/prompts/feature_engineer_system.txt
pond_agent/competition/prompts/feature_engineer_user.txt
pond_agent/competition/prompts/model_builder_system.txt
pond_agent/competition/prompts/model_builder_user.txt
pond_agent/competition/prompts/submission_generator_system.txt
pond_agent/competition/prompts/submission_generator_user.txt
pond_agent-0.1.4.dist-info/METADATA
pond_agent-0.1.4.dist-info/WHEEL
pond_agent-0.1.4.dist-info/licenses/LICENSE
pond_agent-0.1.4.dist-info/RECORD
