Metadata-Version: 2.4
Name: pond-agent
Version: 0.1.4
Summary: AI agents for Pond
Author: bill@cryptopond.xyz
License:                                  Apache License
License-File: LICENSE
Classifier: Development Status :: 3 - Alpha
Classifier: Intended Audience :: Science/Research
Classifier: License :: OSI Approved :: Apache Software License
Classifier: Programming Language :: Python :: 3
Classifier: Programming Language :: Python :: 3.11
Classifier: Topic :: Scientific/Engineering :: Artificial Intelligence
Requires-Python: >=3.11
Requires-Dist: aiofiles
Requires-Dist: aiohttp>=3.9.1
Requires-Dist: anthropic>=0.40.0
Requires-Dist: beautifulsoup4
Requires-Dist: numpy>=2.0.0
Requires-Dist: openai>=1.57.0
Requires-Dist: openpyxl>=3.1.0
Requires-Dist: pandas>=2.0.0
Requires-Dist: playwright>=1.40.0
Requires-Dist: polars>=1.16.0
Requires-Dist: pyarrow>=18.0.0
Requires-Dist: python-dotenv>=1.0.0
Requires-Dist: requests
Requires-Dist: scikit-learn>=1.5.0
Requires-Dist: tabulate
Requires-Dist: torch>=2.0.0
Requires-Dist: tqdm>=4.0.0
Requires-Dist: xgboost>=2.0.0
Provides-Extra: dev
Requires-Dist: build; extra == 'dev'
Requires-Dist: pytest-cov; extra == 'dev'
Requires-Dist: pytest>=8.0.0; extra == 'dev'
Requires-Dist: ruff>=0.6.0; extra == 'dev'
Requires-Dist: twine; extra == 'dev'
